pyroll/lippmann_mahrenholz_force_torque.py
pyroll_lippmann_mahrenholz_force_torque-3.0.1.dist-info/METADATA
pyroll_lippmann_mahrenholz_force_torque-3.0.1.dist-info/WHEEL
pyroll_lippmann_mahrenholz_force_torque-3.0.1.dist-info/licenses/LICENSE
pyroll_lippmann_mahrenholz_force_torque-3.0.1.dist-info/RECORD
