Metadata-Version: 2.4
Name: pyroll-lippmann-mahrenholz-force-torque
Version: 3.0.1
Summary: Plugin for PyRolL providing the power and labour calculation after O. Lippmann and H. Mahrenholz
Project-URL: Homepage, https://pyroll-project.github.io/
Project-URL: Repository, https://github.com/pyroll-project/pyroll-lippmann-mahrenholz-force-torque
Project-URL: Documentation, https://github.com/pyroll-project/pyroll-lippmann-mahrenholz-force-torque/blob/main/docs/docs.pdf
Author-email: Christoph Renzing <christoph.renzing@imf.tu-freiberg.de>
License-Expression: BSD-3-Clause
License-File: LICENSE
Classifier: Intended Audience :: Manufacturing
Classifier: Intended Audience :: Science/Research
Classifier: Operating System :: OS Independent
Classifier: Topic :: Scientific/Engineering
Requires-Python: >=3.9
Requires-Dist: pyroll-core
